checknuit/__init__.py
checknuit/config.py
checknuit/entry.py
checknuit/utils.py
checknuit/web.py
checknuit-0.1.1.dist-info/METADATA
checknuit-0.1.1.dist-info/WHEEL
checknuit-0.1.1.dist-info/top_level.txt
checknuit-0.1.1.dist-info/RECORD
