Metadata-Version: 2.4
Name: checknuit
Version: 0.1.1
Summary: Lib for checking nuit validity, and return nuit data
Author: yannickRafael
Requires-Python: >=3.9
Requires-Dist: requests>=2.31
Requires-Dist: python-dotenv>=1.0
Requires-Dist: beautifulsoup4
